my_package_project/__init__.py
my_package_project/data_treatment.py
my_package_project/graphs.py
my_package_project/my_package_project.py
my_package_project/operations.py
my_package_project-1.3.0.dist-info/LICENSE
my_package_project-1.3.0.dist-info/METADATA
my_package_project-1.3.0.dist-info/WHEEL
my_package_project-1.3.0.dist-info/RECORD
